{"web":{"client_id":"359186578816-fhncct47crvulgbmhj6qboq0i99a1f1q.apps.googleusercontent.com","project_id":"starlit-vim-387301","auth_uri":"https://accounts.google.com/o/oauth2/auth","token_uri":"https://oauth2.googleapis.com/token","auth_provider_x509_cert_url":"https://www.googleapis.com/oauth2/v1/certs","client_secret":"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","redirect_uris":["http://localhost:4200","https://tfipcookado-production.up.railway.app/event","http://localhost:4200/event"],"javascript_origins":["http://localhost:4200"]}}